shap_adaptive_boosting/__init__.py
shap_adaptive_boosting/classifiers.py
shap_adaptive_boosting/explainers.py
shap_adaptive_boosting-1.0.0.dist-info/LICENSE
shap_adaptive_boosting-1.0.0.dist-info/METADATA
shap_adaptive_boosting-1.0.0.dist-info/WHEEL
shap_adaptive_boosting-1.0.0.dist-info/RECORD
