Metadata-Version: 2.3
Name: shap-adaptive-boosting
Version: 1.0.0
Summary: Versions of AdaBoost and RUSBoost compatible with TreeSHAP and respective TreeSHAP Explainers.
Author: Emre Arkan
Author-email: emre.arkan@alexanderthamm.com
Requires-Python: >=3.10
Classifier: Programming Language :: Python :: 3
Classifier: Programming Language :: Python :: 3.10
Classifier: Programming Language :: Python :: 3.11
Classifier: Programming Language :: Python :: 3.12
Classifier: Programming Language :: Python :: 3.13
Requires-Dist: PyYAML (>=6.0,<7.0)
Requires-Dist: bandit[toml] (>=1.7.9,<2.0.0)
Requires-Dist: imbalanced-learn (==0.13.0)
Requires-Dist: importlib-metadata (>=1.0,<2.0) ; python_version < "3.8"
Requires-Dist: matplotlib (>=3.7.2,<4.0.0)
Requires-Dist: pre-commit (>=3.7.0,<4.0.0)
Requires-Dist: pytest (>=8.4.1,<9.0.0)
Requires-Dist: pytest-cov (>=5.0.0,<6.0.0)
Requires-Dist: ruff (>=0.6.3,<0.7.0)
Requires-Dist: shap (==0.48.0)
